[{"__type__":"cc.SpriteFrame","content":{"name":"snowFall023","texture":"08nxFOm8xDW5ho4AGZJbGk","rect":[11,36,622,566],"offset":[2,1],"originalSize":[640,640],"capInsets":[0,0,0,0]}},{"__type__":"cc.SpriteFrame","content":{"name":"snowFall015","texture":"2bfyeanFtCrorUK8UPCMLG","rect":[10,28,621,571],"offset":[0.5,6.5],"originalSize":[640,640],"capInsets":[0,0,0,0]}},{"__type__":"cc.SpriteFrame","content":{"name":"snowFall031","texture":"76Kconx+dPbaGVUPY0UedC","rect":[10,28,622,570],"offset":[1,7],"originalSize":[640,640],"capInsets":[0,0,0,0]}},{"__type__":"cc.SpriteFrame","content":{"name":"snowFall013","texture":"efAiVFJSBJRbErDOaoE9yn","rect":[14,28,618,570],"offset":[3,7],"originalSize":[640,640],"capInsets":[0,0,0,0]}},{"__type__":"cc.SpriteFrame","content":{"name":"snowFall020","texture":"56s3sYM5lNqI98a3Ypys17","rect":[13,28,622,574],"offset":[4,5],"originalSize":[640,640],"capInsets":[0,0,0,0]}},{"__type__":"cc.AnimationClip","_name":"snowFallLeft02","_duration":1.5166666666666666,"wrapMode":2,"curveData":{"paths":{"snowFall001":{"comps":{"cc.Sprite":{"spriteFrame":[{"frame":0,"value":{"__uuid__":"db8gSSKSRDVrpYVu+lFwec"}},{"frame":0.05,"value":{"__uuid__":"931JK1uftCB4e0KA4xY77m"}},{"frame":0.1,"value":{"__uuid__":"7bndmXlBtEa6QB8CzoEORm"}},{"frame":0.15,"value":{"__uuid__":"99taOapaJNjaGwHh1GY4Kf"}},{"frame":0.2,"value":{"__uuid__":"ebCnGPS11L8ovWCyB4Ri5t"}},{"frame":0.25,"value":{"__uuid__":"7bvrP8GDZJvb22+Bln9V9l"}},{"frame":0.3,"value":{"__uuid__":"e2sr5Mu/BI+poNGSeoOl9z"}},{"frame":0.35,"value":{"__uuid__":"b6xgkZv0xM0LsSrvZ+9lml"}},{"frame":0.4,"value":{"__uuid__":"c6oj7wtiRA45QKQ3dS68b4"}},{"frame":0.45,"value":{"__uuid__":"e82oqKuP5I/4OR6rIpl+36"}},{"frame":0.5,"value":{"__uuid__":"eb189ZtBpD0IhKropWKDdr"}},{"frame":0.55,"value":{"__uuid__":"582e/F2rRBMrmPtj0Umkso"}},{"frame":0.6,"value":{"__uuid__":"e5gb7bmgNFd5mpAUKa+DfH"}},{"frame":0.65,"value":{"__uuid__":"4fCmNbxwZAcZ91s9H4lL5S"}},{"frame":0.7,"value":{"__uuid__":"86I0E3n59Oi4RX2bBAIsnZ"}},{"frame":0.75,"value":{"__uuid__":"bf9pbzFL5M5Z6WsLFOXXKH"}},{"frame":0.8,"value":{"__uuid__":"d1AeIMRgNH5577M1/fLTZc"}},{"frame":0.85,"value":{"__uuid__":"beEuiaSmhKHrQV4i/nQ3ZB"}},{"frame":0.9,"value":{"__uuid__":"66LLigWpxIEJRVNOVmepcm"}},{"frame":0.95,"value":{"__uuid__":"e9FUuUAwFB/YRNF1kwVE3u"}},{"frame":1,"value":{"__uuid__":"ddVY4l2eZBXobKQ+ds8eCT"}},{"frame":1.05,"value":{"__uuid__":"4dy/2AGmRHs6rrnO0AZ7WB"}},{"frame":1.1,"value":{"__uuid__":"e7jLNrpIRPXJ1fW4FhPp7R"}},{"frame":1.15,"value":{"__uuid__":"fdsCL1qv1Cc6NOfs68jrit"}},{"frame":1.2,"value":{"__uuid__":"d5zDsmRv1Nro+Y53ElFuga"}},{"frame":1.25,"value":{"__uuid__":"b57gAGmNNCD5a8zVfUUoeb"}},{"frame":1.3,"value":{"__uuid__":"dcKLzY0M1DVYXR5z/itZLq"}},{"frame":1.35,"value":{"__uuid__":"70diuE7yVAKZg79pPL06zz"}},{"frame":1.4,"value":{"__uuid__":"7bOefstC1MyogRyvTQUCta"}},{"frame":1.45,"value":{"__uuid__":"52lwKKf71JLqSslSTyKKcv"}},{"frame":1.5,"value":{"__uuid__":"f0aCPExVJGcpeMS+RXgZOi"}}]}}},"snowFall002":{"comps":{"cc.Sprite":{"spriteFrame":[{"frame":0,"value":{"__uuid__":"db8gSSKSRDVrpYVu+lFwec"}},{"frame":0.05,"value":{"__uuid__":"931JK1uftCB4e0KA4xY77m"}},{"frame":0.1,"value":{"__uuid__":"7bndmXlBtEa6QB8CzoEORm"}},{"frame":0.15,"value":{"__uuid__":"99taOapaJNjaGwHh1GY4Kf"}},{"frame":0.2,"value":{"__uuid__":"ebCnGPS11L8ovWCyB4Ri5t"}},{"frame":0.25,"value":{"__uuid__":"7bvrP8GDZJvb22+Bln9V9l"}},{"frame":0.3,"value":{"__uuid__":"e2sr5Mu/BI+poNGSeoOl9z"}},{"frame":0.35,"value":{"__uuid__":"b6xgkZv0xM0LsSrvZ+9lml"}},{"frame":0.4,"value":{"__uuid__":"c6oj7wtiRA45QKQ3dS68b4"}},{"frame":0.45,"value":{"__uuid__":"e82oqKuP5I/4OR6rIpl+36"}},{"frame":0.5,"value":{"__uuid__":"eb189ZtBpD0IhKropWKDdr"}},{"frame":0.55,"value":{"__uuid__":"582e/F2rRBMrmPtj0Umkso"}},{"frame":0.6,"value":{"__uuid__":"e5gb7bmgNFd5mpAUKa+DfH"}},{"frame":0.65,"value":{"__uuid__":"4fCmNbxwZAcZ91s9H4lL5S"}},{"frame":0.7,"value":{"__uuid__":"86I0E3n59Oi4RX2bBAIsnZ"}},{"frame":0.75,"value":{"__uuid__":"bf9pbzFL5M5Z6WsLFOXXKH"}},{"frame":0.8,"value":{"__uuid__":"d1AeIMRgNH5577M1/fLTZc"}},{"frame":0.85,"value":{"__uuid__":"beEuiaSmhKHrQV4i/nQ3ZB"}},{"frame":0.9,"value":{"__uuid__":"66LLigWpxIEJRVNOVmepcm"}},{"frame":0.95,"value":{"__uuid__":"e9FUuUAwFB/YRNF1kwVE3u"}},{"frame":1,"value":{"__uuid__":"ddVY4l2eZBXobKQ+ds8eCT"}},{"frame":1.05,"value":{"__uuid__":"4dy/2AGmRHs6rrnO0AZ7WB"}},{"frame":1.1,"value":{"__uuid__":"e7jLNrpIRPXJ1fW4FhPp7R"}},{"frame":1.15,"value":{"__uuid__":"fdsCL1qv1Cc6NOfs68jrit"}},{"frame":1.2,"value":{"__uuid__":"d5zDsmRv1Nro+Y53ElFuga"}},{"frame":1.25,"value":{"__uuid__":"b57gAGmNNCD5a8zVfUUoeb"}},{"frame":1.3,"value":{"__uuid__":"dcKLzY0M1DVYXR5z/itZLq"}},{"frame":1.35,"value":{"__uuid__":"70diuE7yVAKZg79pPL06zz"}},{"frame":1.4,"value":{"__uuid__":"7bOefstC1MyogRyvTQUCta"}},{"frame":1.45,"value":{"__uuid__":"52lwKKf71JLqSslSTyKKcv"}},{"frame":1.5,"value":{"__uuid__":"f0aCPExVJGcpeMS+RXgZOi"}}]}}},"snowFall003":{"comps":{"cc.Sprite":{"spriteFrame":[{"frame":0,"value":{"__uuid__":"db8gSSKSRDVrpYVu+lFwec"}},{"frame":0.05,"value":{"__uuid__":"931JK1uftCB4e0KA4xY77m"}},{"frame":0.1,"value":{"__uuid__":"7bndmXlBtEa6QB8CzoEORm"}},{"frame":0.15,"value":{"__uuid__":"99taOapaJNjaGwHh1GY4Kf"}},{"frame":0.2,"value":{"__uuid__":"ebCnGPS11L8ovWCyB4Ri5t"}},{"frame":0.25,"value":{"__uuid__":"7bvrP8GDZJvb22+Bln9V9l"}},{"frame":0.3,"value":{"__uuid__":"e2sr5Mu/BI+poNGSeoOl9z"}},{"frame":0.35,"value":{"__uuid__":"b6xgkZv0xM0LsSrvZ+9lml"}},{"frame":0.4,"value":{"__uuid__":"c6oj7wtiRA45QKQ3dS68b4"}},{"frame":0.45,"value":{"__uuid__":"e82oqKuP5I/4OR6rIpl+36"}},{"frame":0.5,"value":{"__uuid__":"eb189ZtBpD0IhKropWKDdr"}},{"frame":0.55,"value":{"__uuid__":"582e/F2rRBMrmPtj0Umkso"}},{"frame":0.6,"value":{"__uuid__":"e5gb7bmgNFd5mpAUKa+DfH"}},{"frame":0.65,"value":{"__uuid__":"4fCmNbxwZAcZ91s9H4lL5S"}},{"frame":0.7,"value":{"__uuid__":"86I0E3n59Oi4RX2bBAIsnZ"}},{"frame":0.75,"value":{"__uuid__":"bf9pbzFL5M5Z6WsLFOXXKH"}},{"frame":0.8,"value":{"__uuid__":"d1AeIMRgNH5577M1/fLTZc"}},{"frame":0.85,"value":{"__uuid__":"beEuiaSmhKHrQV4i/nQ3ZB"}},{"frame":0.9,"value":{"__uuid__":"66LLigWpxIEJRVNOVmepcm"}},{"frame":0.95,"value":{"__uuid__":"e9FUuUAwFB/YRNF1kwVE3u"}},{"frame":1,"value":{"__uuid__":"ddVY4l2eZBXobKQ+ds8eCT"}},{"frame":1.05,"value":{"__uuid__":"4dy/2AGmRHs6rrnO0AZ7WB"}},{"frame":1.1,"value":{"__uuid__":"e7jLNrpIRPXJ1fW4FhPp7R"}},{"frame":1.15,"value":{"__uuid__":"fdsCL1qv1Cc6NOfs68jrit"}},{"frame":1.2,"value":{"__uuid__":"d5zDsmRv1Nro+Y53ElFuga"}},{"frame":1.25,"value":{"__uuid__":"b57gAGmNNCD5a8zVfUUoeb"}},{"frame":1.3,"value":{"__uuid__":"dcKLzY0M1DVYXR5z/itZLq"}},{"frame":1.35,"value":{"__uuid__":"70diuE7yVAKZg79pPL06zz"}},{"frame":1.4,"value":{"__uuid__":"7bOefstC1MyogRyvTQUCta"}},{"frame":1.45,"value":{"__uuid__":"52lwKKf71JLqSslSTyKKcv"}},{"frame":1.5,"value":{"__uuid__":"f0aCPExVJGcpeMS+RXgZOi"}}]}}}}}},{"__type__":"cc.SpriteFrame","content":{"name":"snowFall029","texture":"77nCL41zFDz4O8bGV0D2wd","rect":[10,28,623,573],"offset":[1.5,5.5],"originalSize":[640,640],"capInsets":[0,0,0,0]}},{"__type__":"cc.SpriteFrame","content":{"name":"snowFall030","texture":"46DGmwFQFJVpFfzC97KwYu","rect":[10,28,624,574],"offset":[2,5],"originalSize":[640,640],"capInsets":[0,0,0,0]}},{"__type__":"cc.SpriteFrame","content":{"name":"snowFall003","texture":"1afMWe4d9B2pm3Jc6tX2cB","rect":[10,28,623,573],"offset":[1.5,5.5],"originalSize":[640,640],"capInsets":[0,0,0,0]}},{"__type__":"cc.SpriteFrame","content":{"name":"snowFall006","texture":"08BNxz+QNGFLQBg05+YNzo","rect":[10,28,623,573],"offset":[1.5,5.5],"originalSize":[640,640],"capInsets":[0,0,0,0]}},{"__type__":"cc.SpriteFrame","content":{"name":"snowFall016","texture":"2fk3yMw0VBHZH5sW8Gndym","rect":[11,28,621,572],"offset":[1.5,6],"originalSize":[640,640],"capInsets":[0,0,0,0]}},{"__type__":"cc.SpriteFrame","content":{"name":"snowFall002","texture":"bbRojbvO5G5bk80yIihR//","rect":[10,28,623,572],"offset":[1.5,6],"originalSize":[640,640],"capInsets":[0,0,0,0]}},{"__type__":"cc.SpriteFrame","content":{"name":"snowFall004","texture":"ae0xrcbkVMtJ5oGWveKr/8","rect":[10,28,623,565],"offset":[1.5,9.5],"originalSize":[640,640],"capInsets":[0,0,0,0]}},{"__type__":"cc.SpriteFrame","content":{"name":"snowFall027","texture":"3bQaizIWhIG4iQ8myw6N9J","rect":[11,28,622,571],"offset":[2,6.5],"originalSize":[640,640],"capInsets":[0,0,0,0]}},{"__type__":"cc.SpriteFrame","content":{"name":"snowFall008","texture":"98EB8P4v5JkYH1GGS3gE16","rect":[18,28,615,574],"offset":[5.5,5],"originalSize":[640,640],"capInsets":[0,0,0,0]}},{"__type__":"cc.SpriteFrame","content":{"name":"snowFall019","texture":"9fNZXGeSNLbbjGU5M/MwvQ","rect":[13,28,620,574],"offset":[3,5],"originalSize":[640,640],"capInsets":[0,0,0,0]}},{"__type__":"cc.SpriteFrame","content":{"name":"snowFall017","texture":"3e3NwJLWpAHYebCMlw8h2k","rect":[12,28,620,573],"offset":[2,5.5],"originalSize":[640,640],"capInsets":[0,0,0,0]}},{"__type__":"cc.SpriteFrame","content":{"name":"snowFall010","texture":"54+TdyPi1ARKq9DC0H3dRD","rect":[17,28,618,566],"offset":[6,9],"originalSize":[640,640],"capInsets":[0,0,0,0]}},{"__type__":"cc.SpriteFrame","content":{"name":"snowFall018","texture":"6cGMQTxStCionY7rWgfM1z","rect":[13,28,620,574],"offset":[3,5],"originalSize":[640,640],"capInsets":[0,0,0,0]}},{"__type__":"cc.SpriteFrame","content":{"name":"snowFall026","texture":"65ywsw0ltOGae6eQO1dEdw","rect":[11,28,622,572],"offset":[2,6],"originalSize":[640,640],"capInsets":[0,0,0,0]}},{"__type__":"cc.SpriteFrame","content":{"name":"snowFall001","texture":"f2pz9ubQRG46XztCGlgaCM","rect":[10,28,623,573],"offset":[1.5,5.5],"originalSize":[640,640],"capInsets":[0,0,0,0]}},{"__type__":"cc.SpriteFrame","content":{"name":"snowFall028","texture":"d9E4O3To1HgJUjVKhwm5dp","rect":[10,28,623,573],"offset":[1.5,5.5],"originalSize":[640,640],"capInsets":[0,0,0,0]}},{"__type__":"cc.SpriteFrame","content":{"name":"snowFall022","texture":"efF3GInpNAj7yAeFvpozFF","rect":[12,32,621,568],"offset":[2.5,4],"originalSize":[640,640],"capInsets":[0,0,0,0]}},{"__type__":"cc.SpriteFrame","content":{"name":"snowFall007","texture":"e4B6p77nhKs6QuTRoBSuTv","rect":[18,28,615,573],"offset":[5.5,5.5],"originalSize":[640,640],"capInsets":[0,0,0,0]}},{"__type__":"cc.SpriteFrame","content":{"name":"snowFall014","texture":"28+HOkGg5CtIuvI545NsTN","rect":[10,28,622,572],"offset":[1,6],"originalSize":[640,640],"capInsets":[0,0,0,0]}},{"__type__":"cc.SpriteFrame","content":{"name":"snowFall024","texture":"b5dwfARJJCoKtTPaaoV2Dj","rect":[10,28,623,573],"offset":[1.5,5.5],"originalSize":[640,640],"capInsets":[0,0,0,0]}},{"__type__":"cc.SpriteFrame","content":{"name":"snowFall011","texture":"01EN3YMGVEzKPhBssxuyIp","rect":[11,28,622,567],"offset":[2,8.5],"originalSize":[640,640],"capInsets":[0,0,0,0]}},{"__type__":"cc.SpriteFrame","content":{"name":"snowFall021","texture":"c4z1w6BkRBuqxdJYlat6+/","rect":[13,28,620,570],"offset":[3,7],"originalSize":[640,640],"capInsets":[0,0,0,0]}},{"__type__":"cc.SpriteFrame","content":{"name":"snowFall005","texture":"dfwXhmk09O9q6vK/XLCaPt","rect":[10,28,623,569],"offset":[1.5,7.5],"originalSize":[640,640],"capInsets":[0,0,0,0]}},{"__type__":"cc.SpriteFrame","content":{"name":"snowFall012","texture":"2eRWY8bSlPXov5wMThDtBH","rect":[13,28,619,569],"offset":[2.5,7.5],"originalSize":[640,640],"capInsets":[0,0,0,0]}},{"__type__":"cc.SpriteFrame","content":{"name":"snowFall032","texture":"b09LAmgqtAyot38yyUMuUl","rect":[10,28,623,572],"offset":[1.5,6],"originalSize":[640,640],"capInsets":[0,0,0,0]}},{"__type__":"cc.SpriteFrame","content":{"name":"snowFall025","texture":"5eXnEaq8ZIC63FvVAdXAo5","rect":[10,28,623,570],"offset":[1.5,7],"originalSize":[640,640],"capInsets":[0,0,0,0]}}]